networkg-0.1.4.dist-info/METADATA
networkg-0.1.4.dist-info/WHEEL
networkg/graph.py
networkg/__init__.py
networkg/networkg.cp39-win_amd64.pyd
networkg-0.1.4.dist-info/RECORD
