Metadata-Version: 2.1
Name: networkg
Version: 0.1.4
Classifier: License :: OSI Approved :: MIT License
Classifier: Programming Language :: Rust
Classifier: Programming Language :: Python :: 3.7
Classifier: Programming Language :: Python :: 3.8
Classifier: Programming Language :: Python :: 3.9
Requires-Dist: importlib_metadata==3.3.0;python_version<"3.8"
Project-Url: Repository, https://github.com/gustavgransbo/networkg/
Project-Url: Documentation, https://networkg.readthedocs.io/
Home-Page: https://github.com/gustavgransbo/networkg/
Author: Gustav Gränsbo <gustav.gransbo@gmail.com>
Author-Email: Gustav Gränsbo <gustav.gransbo@gmail.com>
License: MIT
Requires-Python: >=3.7
